LICENSE
MANIFEST.in
README.rst
setup.cfg
setup.py
docs/Makefile
docs/authors.rst
docs/conf.py
docs/contributing.rst
docs/history.rst
docs/index.rst
docs/installation.rst
docs/make.bat
docs/readme.rst
docs/usage.rst
fizzbotz/__init__.py
fizzbotz/exceptions.py
fizzbotz/responses.py
fizzbotz/util.py
fizzbotz.egg-info/PKG-INFO
fizzbotz.egg-info/SOURCES.txt
fizzbotz.egg-info/dependency_links.txt
fizzbotz.egg-info/not-zip-safe
fizzbotz.egg-info/requires.txt
fizzbotz.egg-info/top_level.txt
fizzbotz/__pycache__/__init__.cpython-35.pyc
fizzbotz/__pycache__/exceptions.cpython-35.pyc
fizzbotz/__pycache__/responses.cpython-35.pyc
fizzbotz/__pycache__/util.cpython-35.pyc
tests/test_responses.py
tests/test_util.py
tests/__pycache__/test_responses.cpython-35-PYTEST.pyc
tests/__pycache__/test_util.cpython-35-PYTEST.pyc
tests/test_files/bestoftwitchchat.html
tests/test_files/bestoftwitchchat.txt
tests/test_files/httpbin_html.html
tests/test_files/insult.html
tests/test_files/insult.txt
tests/test_files/joke_oneliner.html
tests/test_files/joke_oneliner.txt
tests/test_files/joke_oneliner_quote.html
tests/test_files/joke_oneliner_quote.txt
tests/test_files/twitchquotes.html
tests/test_files/twitchquotes.txt
tests/test_files/twitchquotes_emotes.html
tests/test_files/twitchquotes_emotes.txt
tests/test_files/twitchquotes_text_art.html
tests/test_files/twitchquotes_text_art.txt
tests/test_files/twitchquotes_unicode.html
tests/test_files/twitchquotes_unicode.txt