Metadata-Version: 1.1
Name: fizzbotz
Version: 0.2.0
Summary: A bot for discord written in Python implementing some basic commands.
Home-page: https://github.com/martensm/fizzbotz
Author: Matthew Martens
Author-email: matthew.s.martens@gmail.com
License: MIT
Keywords: fizzbotz
Platform: UNKNOWN
Classifier: Development Status :: 2 - Pre-Alpha
Classifier: Intended Audience :: Developers
Classifier: License :: OSI Approved :: MIT License
Classifier: Natural Language :: English
Classifier: Programming Language :: Python :: 3
Classifier: Programming Language :: Python :: 3.5
